aioseedrcc/__init__.py
aioseedrcc/exception.py
aioseedrcc/login.py
aioseedrcc/seedr.py
aioseedrcc-0.3.2.dist-info/LICENSE
aioseedrcc-0.3.2.dist-info/METADATA
aioseedrcc-0.3.2.dist-info/WHEEL
aioseedrcc-0.3.2.dist-info/RECORD
