Metadata-Version: 2.1
Name: aioseedrcc
Version: 0.3.2
Summary: AIOSeedrcc is a Python asyncrnous library for interacting with Seedr.cc API.
Home-page: https://aioseedrcc.rtfd.io
License: MIT
Keywords: seedr,seedr.cc,torrent,api,asyncio,aiohttp
Author: mhdzumair
Author-email: mhdzumair@gmail.com
Requires-Python: >=3.10
Classifier: License :: OSI Approved :: MIT License
Classifier: Programming Language :: Python :: 3
Classifier: Programming Language :: Python :: 3.10
Classifier: Programming Language :: Python :: 3.11
Classifier: Programming Language :: Python :: 3.12
Classifier: Programming Language :: Python :: 3.13
Requires-Dist: aiofiles (>=24.1.0,<25.0.0)
Requires-Dist: aiohttp (>=3.10.10,<4.0.0)
Project-URL: Documentation, https://aioseedrcc.rtfd.io
Project-URL: Repository, https://github.com/mhdzumair/aioseedrcc
